Workbook

Sheet Start Here
B2: LedgerLite — Shop Sales Tracker
B4: Track your own shop here — see what sells and what you actually keep.
B5: 1. Each time you make a sale, add a row on the Sales tab: date, which listing, the platform, units, the gross price, and the fees the platform took.
B6: 2. Net is calculated for you (gross − fees) — that's what you actually keep.
B7: 3. The Dashboard shows totals, your best-selling listings, and a breakdown by platform and month.
B8: Tip: for Etsy, fees ≈ 6.5% transaction + ~3% + $0.25 payment + $0.20 listing. Gumroad ≈ 10% + fees. Enter the actual fees from your payout for accuracy.
B9: This is your private business record — not tax advice. Keep your own receipts for filing.

Sheet Lists
A1: Short-Term Rental Tracker | B1: Etsy
A2: Rental Property Tracker | B2: Gumroad
A3: Online Seller Tracker | B3: Payhip
A4: Freelancer Tracker | B4: Other
A5: Real Estate Agent Tracker
A6: Photographer Tracker
A7: Cleaning Business Tracker
A8: Hair Stylist & Beauty Tracker
A9: Rideshare & Delivery Tracker
A10: Food Truck & Vendor Tracker
A11: Rental Investor Bundle
A12: Self-Employed Bundle
A13: Everything Bundle

Sheet Sales
A1: Sales — add one row per order
A3: Date | B3: Listing | C3: Platform | D3: Units | E3: Gross $ | F3: Fees $ | G3: Net $ | H3: Month | I3: Notes
A4: 46175 | B4: Online Seller Tracker | C4: Etsy | D4: 1 | E4: 19 | F4: 2.05 | G4: =IF(E4="","",E4-F4) | H4: =IF(A4="","",TEXT(A4,"yyyy-mm"))
A5: 46176 | B5: Everything Bundle | C5: Gumroad | D5: 1 | E5: 69 | F5: 7.2 | G5: =IF(E5="","",E5-F5) | H5: =IF(A5="","",TEXT(A5,"yyyy-mm"))
A6: 46178 | B6: Real Estate Agent Tracker | C6: Etsy | D6: 1 | E6: 24 | F6: 2.45 | G6: =IF(E6="","",E6-F6) | H6: =IF(A6="","",TEXT(A6,"yyyy-mm"))
G7: =IF(E7="","",E7-F7) | H7: =IF(A7="","",TEXT(A7,"yyyy-mm"))
G8: =IF(E8="","",E8-F8) | H8: =IF(A8="","",TEXT(A8,"yyyy-mm"))
G9: =IF(E9="","",E9-F9) | H9: =IF(A9="","",TEXT(A9,"yyyy-mm"))
G10: =IF(E10="","",E10-F10) | H10: =IF(A10="","",TEXT(A10,"yyyy-mm"))
G11: =IF(E11="","",E11-F11) | H11: =IF(A11="","",TEXT(A11,"yyyy-mm"))
G12: =IF(E12="","",E12-F12) | H12: =IF(A12="","",TEXT(A12,"yyyy-mm"))
G13: =IF(E13="","",E13-F13) | H13: =IF(A13="","",TEXT(A13,"yyyy-mm"))
G14: =IF(E14="","",E14-F14) | H14: =IF(A14="","",TEXT(A14,"yyyy-mm"))
G15: =IF(E15="","",E15-F15) | H15: =IF(A15="","",TEXT(A15,"yyyy-mm"))
G16: =IF(E16="","",E16-F16) | H16: =IF(A16="","",TEXT(A16,"yyyy-mm"))
G17: =IF(E17="","",E17-F17) | H17: =IF(A17="","",TEXT(A17,"yyyy-mm"))
G18: =IF(E18="","",E18-F18) | H18: =IF(A18="","",TEXT(A18,"yyyy-mm"))
... G603: =IF(E603="","",E603-F603) | H603: =IF(A603="","",TEXT(A603,"yyyy-mm"))

Sheet Dashboard
B2: Shop Dashboard — live
B4: Gross sales | C4: Fees | D4: Net (you keep) | G4: Units sold
B5: =SUM(Sales!$E$4:$E$603) | C5: =SUM(Sales!$F$4:$F$603) | D5: =SUM(Sales!$G$4:$G$603) | G5: =SUM(Sales!$D$4:$D$603)
B8: By listing | G8: By platform
B9: Listing | C9: Units | D9: Net $ | G9: Platform | H9: Net $ | I9: Units
B10: Short-Term Rental Tracker | C10: =SUMIFS(Sales!$D$4:$D$603,Sales!$B$4:$B$603,$B10) | D10: =SUMIFS(Sales!$G$4:$G$603,Sales!$B$4:$B$603,$B10) | G10: Etsy | H10: =SUMIFS(Sales!$G$4:$G$603,Sales!$C$4:$C$603,$G10) | I10: =SUMIFS(Sales!$D$4:$D$603,Sales!$C$4:$C$603,$G10)
B11: Rental Property Tracker | C11: =SUMIFS(Sales!$D$4:$D$603,Sales!$B$4:$B$603,$B11) | D11: =SUMIFS(Sales!$G$4:$G$603,Sales!$B$4:$B$603,$B11) | G11: Gumroad | H11: =SUMIFS(Sales!$G$4:$G$603,Sales!$C$4:$C$603,$G11) | I11: =SUMIFS(Sales!$D$4:$D$603,Sales!$C$4:$C$603,$G11)
B12: Online Seller Tracker | C12: =SUMIFS(Sales!$D$4:$D$603,Sales!$B$4:$B$603,$B12) | D12: =SUMIFS(Sales!$G$4:$G$603,Sales!$B$4:$B$603,$B12) | G12: Payhip | H12: =SUMIFS(Sales!$G$4:$G$603,Sales!$C$4:$C$603,$G12) | I12: =SUMIFS(Sales!$D$4:$D$603,Sales!$C$4:$C$603,$G12)
B13: Freelancer Tracker | C13: =SUMIFS(Sales!$D$4:$D$603,Sales!$B$4:$B$603,$B13) | D13: =SUMIFS(Sales!$G$4:$G$603,Sales!$B$4:$B$603,$B13) | G13: Other | H13: =SUMIFS(Sales!$G$4:$G$603,Sales!$C$4:$C$603,$G13) | I13: =SUMIFS(Sales!$D$4:$D$603,Sales!$C$4:$C$603,$G13)
B14: Real Estate Agent Tracker | C14: =SUMIFS(Sales!$D$4:$D$603,Sales!$B$4:$B$603,$B14) | D14: =SUMIFS(Sales!$G$4:$G$603,Sales!$B$4:$B$603,$B14)
B15: Photographer Tracker | C15: =SUMIFS(Sales!$D$4:$D$603,Sales!$B$4:$B$603,$B15) | D15: =SUMIFS(Sales!$G$4:$G$603,Sales!$B$4:$B$603,$B15) | G15: By month (2026)
B16: Cleaning Business Tracker | C16: =SUMIFS(Sales!$D$4:$D$603,Sales!$B$4:$B$603,$B16) | D16: =SUMIFS(Sales!$G$4:$G$603,Sales!$B$4:$B$603,$B16) | G16: Month | H16: Net $ | I16: Units
B17: Hair Stylist & Beauty Tracker | C17: =SUMIFS(Sales!$D$4:$D$603,Sales!$B$4:$B$603,$B17) | D17: =SUMIFS(Sales!$G$4:$G$603,Sales!$B$4:$B$603,$B17) | G17: 2026-01 | H17: =SUMIFS(Sales!$G$4:$G$603,Sales!$H$4:$H$603,$G17) | I17: =SUMIFS(Sales!$D$4:$D$603,Sales!$H$4:$H$603,$G17)
B18: Rideshare & Delivery Tracker | C18: =SUMIFS(Sales!$D$4:$D$603,Sales!$B$4:$B$603,$B18) | D18: =SUMIFS(Sales!$G$4:$G$603,Sales!$B$4:$B$603,$B18) | G18: 2026-02 | H18: =SUMIFS(Sales!$G$4:$G$603,Sales!$H$4:$H$603,$G18) | I18: =SUMIFS(Sales!$D$4:$D$603,Sales!$H$4:$H$603,$G18)
B19: Food Truck & Vendor Tracker | C19: =SUMIFS(Sales!$D$4:$D$603,Sales!$B$4:$B$603,$B19) | D19: =SUMIFS(Sales!$G$4:$G$603,Sales!$B$4:$B$603,$B19) | G19: 2026-03 | H19: =SUMIFS(Sales!$G$4:$G$603,Sales!$H$4:$H$603,$G19) | I19: =SUMIFS(Sales!$D$4:$D$603,Sales!$H$4:$H$603,$G19)
B20: Rental Investor Bundle | C20: =SUMIFS(Sales!$D$4:$D$603,Sales!$B$4:$B$603,$B20) | D20: =SUMIFS(Sales!$G$4:$G$603,Sales!$B$4:$B$603,$B20) | G20: 2026-04 | H20: =SUMIFS(Sales!$G$4:$G$603,Sales!$H$4:$H$603,$G20) | I20: =SUMIFS(Sales!$D$4:$D$603,Sales!$H$4:$H$603,$G20)
B21: Self-Employed Bundle | C21: =SUMIFS(Sales!$D$4:$D$603,Sales!$B$4:$B$603,$B21) | D21: =SUMIFS(Sales!$G$4:$G$603,Sales!$B$4:$B$603,$B21) | G21: 2026-05 | H21: =SUMIFS(Sales!$G$4:$G$603,Sales!$H$4:$H$603,$G21) | I21: =SUMIFS(Sales!$D$4:$D$603,Sales!$H$4:$H$603,$G21)
B22: Everything Bundle | C22: =SUMIFS(Sales!$D$4:$D$603,Sales!$B$4:$B$603,$B22) | D22: =SUMIFS(Sales!$G$4:$G$603,Sales!$B$4:$B$603,$B22) | G22: 2026-06 | H22: =SUMIFS(Sales!$G$4:$G$603,Sales!$H$4:$H$603,$G22) | I22: =SUMIFS(Sales!$D$4:$D$603,Sales!$H$4:$H$603,$G22)
G23: 2026-07 | H23: =SUMIFS(Sales!$G$4:$G$603,Sales!$H$4:$H$603,$G23) | I23: =SUMIFS(Sales!$D$4:$D$603,Sales!$H$4:$H$603,$G23)
G24: 2026-08 | H24: =SUMIFS(Sales!$G$4:$G$603,Sales!$H$4:$H$603,$G24) | I24: =SUMIFS(Sales!$D$4:$D$603,Sales!$H$4:$H$603,$G24)
G25: 2026-09 | H25: =SUMIFS(Sales!$G$4:$G$603,Sales!$H$4:$H$603,$G25) | I25: =SUMIFS(Sales!$D$4:$D$603,Sales!$H$4:$H$603,$G25)
G26: 2026-10 | H26: =SUMIFS(Sales!$G$4:$G$603,Sales!$H$4:$H$603,$G26) | I26: =SUMIFS(Sales!$D$4:$D$603,Sales!$H$4:$H$603,$G26)
G27: 2026-11 | H27: =SUMIFS(Sales!$G$4:$G$603,Sales!$H$4:$H$603,$G27) | I27: =SUMIFS(Sales!$D$4:$D$603,Sales!$H$4:$H$603,$G27)
G28: 2026-12 | H28: =SUMIFS(Sales!$G$4:$G$603,Sales!$H$4:$H$603,$G28) | I28: =SUMIFS(Sales!$D$4:$D$603,Sales!$H$4:$H$603,$G28)
