Workbook

Sheet Start Here
B2: Online Seller — Bookkeeping & Tax Tracker
B3: Etsy / Amazon / Shopify / craft-fair sellers · IRS Schedule C ready · works in Excel & Google Sheets
B5: How this works
B6: 1. Open the Setup tab and type your shop names (up to 5). Everything else links to these names automatically.
B7: 2. Each time money moves, add one row on the Transactions tab. Pick the shop, choose Income or Expense, and pick a category from the dropdown. That's it.
B8: 3. The Schedule C Summary tab fills itself in — every expense is mapped to the correct IRS Schedule C line, per shop. Hand it straight to your accountant or copy the totals into your tax software.
B9: 4. The Dashboard tab updates live: net profit, income vs. expenses, totals by shop and by month.
B10: Tips
B11: • Categories live on the Categories tab. The dropdowns read from there, so you never mistype a category.
B12: • Log gross sales as income and the marketplace's cut (Etsy/Amazon/PayPal/Square fees) as a 'Commissions & marketplace fees' expense — don't net them together.
B13: • Materials and inventory you buy to make or resell products go under 'Cost of goods sold (materials)'; packaging goes under 'Supplies & packaging'.
B14: • Duplicate the file per tax year (e.g. 'Online Seller 2026').
... B16: This template is a bookkeeping organizer, not tax, legal, or accounting advice. Schedule C line mapping is provided for convenience — confirm your specific situation with a qualified tax professional.

Sheet Setup
B2: Shop Setup
B3: Type each shop's name below. These names feed every dropdown and report.
B5: Shop name | C5: Notes (optional) | D5: Platform | E5: Start date (optional)
B6: Etsy Shop
B7: Amazon Store
B8: Craft Fairs

Sheet Categories
H1: All categories (dropdown source) | J1: Type
B2: Categories & Schedule C mapping | H2: Product sales | J2: Income
H3: Shipping income collected | J3: Expense
B4: Expense category | C4: Schedule C line | E4: Income category | H4: Other income
B5: Advertising & promotion | C5: 8 Advertising | E5: Product sales | H5: Advertising & promotion
B6: Car & truck | C6: 9 Car & truck | E6: Shipping income collected | H6: Car & truck
B7: Commissions & marketplace fees | C7: 10 Commissions & fees | E7: Other income | H7: Commissions & marketplace fees
B8: Contract labor | C8: 11 Contract labor | H8: Contract labor
B9: Cost of goods sold (materials) | C9: 4 Cost of goods sold | H9: Cost of goods sold (materials)
B10: Insurance (business) | C10: 15 Insurance | H10: Insurance (business)
B11: Legal & professional | C11: 17 Legal & professional | H11: Legal & professional
B12: Office expense | C12: 18 Office expense | H12: Office expense
B13: Rent or lease | C13: 20 Rent or lease | H13: Rent or lease
B14: Repairs & maintenance | C14: 21 Repairs & maintenance | H14: Repairs & maintenance
B15: Shipping & postage | C15: 27 Other (shipping) | H15: Shipping & postage
B16: Software & subscriptions | C16: 27 Other (software) | H16: Software & subscriptions
B17: Supplies & packaging | C17: 22 Supplies | H17: Supplies & packaging
B18: Taxes & licenses | C18: 23 Taxes & licenses | H18: Taxes & licenses
B19: Travel & meals | C19: 24 Travel & meals | H19: Travel & meals
B20: Utilities (phone/internet) | C20: 25 Utilities | H20: Utilities (phone/internet)

Sheet Transactions
A1: Transactions — add one row per income or expense
A3: Date | B3: Shop | C3: Type | D3: Category | E3: Description | F3: Amount | G3: Customer / payee | H3: Month | I3: Notes
A4: 46144 | B4: Etsy Shop | C4: Income | D4: Product sales | E4: Orders #1001–1010 | F4: 980 | G4: Etsy | H4: =IF(A4="","",TEXT(A4,"yyyy-mm"))
A5: 46144 | B5: Etsy Shop | C5: Expense | D5: Commissions & marketplace fees | E5: Etsy transaction + payment | F5: 88.2 | G5: Etsy | H5: =IF(A5="","",TEXT(A5,"yyyy-mm"))
A6: 46146 | B6: Etsy Shop | C6: Expense | D6: Cost of goods sold (materials) | E6: Yarn + beads restock | F6: 145 | G6: Supplier | H6: =IF(A6="","",TEXT(A6,"yyyy-mm"))
A7: 46148 | B7: Etsy Shop | C7: Expense | D7: Shipping & postage | E7: May postage labels | F7: 62.4 | G7: USPS | H7: =IF(A7="","",TEXT(A7,"yyyy-mm"))
A8: 46151 | B8: Amazon Store | C8: Income | D8: Product sales | E8: FBA payout | F8: 1320 | G8: Amazon | H8: =IF(A8="","",TEXT(A8,"yyyy-mm"))
A9: 46151 | B9: Amazon Store | C9: Expense | D9: Commissions & marketplace fees | E9: Amazon referral + FBA fees | F9: 264 | G9: Amazon | H9: =IF(A9="","",TEXT(A9,"yyyy-mm"))
A10: 46157 | B10: Etsy Shop | C10: Expense | D10: Software & subscriptions | E10: Canva + email tool | F10: 29 | G10: SaaS | H10: =IF(A10="","",TEXT(A10,"yyyy-mm"))
A11: 46162 | B11: Craft Fairs | C11: Income | D11: Product sales | E11: Spring market booth | F11: 410 | G11: Square | H11: =IF(A11="","",TEXT(A11,"yyyy-mm"))
H12: =IF(A12="","",TEXT(A12,"yyyy-mm"))
H13: =IF(A13="","",TEXT(A13,"yyyy-mm"))
H14: =IF(A14="","",TEXT(A14,"yyyy-mm"))
H15: =IF(A15="","",TEXT(A15,"yyyy-mm"))
H16: =IF(A16="","",TEXT(A16,"yyyy-mm"))
H17: =IF(A17="","",TEXT(A17,"yyyy-mm"))
H18: =IF(A18="","",TEXT(A18,"yyyy-mm"))
H19: =IF(A19="","",TEXT(A19,"yyyy-mm"))
H20: =IF(A20="","",TEXT(A20,"yyyy-mm"))
H21: =IF(A21="","",TEXT(A21,"yyyy-mm"))
H22: =IF(A22="","",TEXT(A22,"yyyy-mm"))
H23: =IF(A23="","",TEXT(A23,"yyyy-mm"))
... H1003: =IF(A1003="","",TEXT(A1003,"yyyy-mm"))

Sheet Schedule C Summary
B2: Schedule C Summary — auto-calculated per shop
B4: Schedule C line | C4: =Setup!$B$6 | D4: =Setup!$B$7 | E4: =Setup!$B$8 | F4: =Setup!$B$9 | G4: =Setup!$B$10 | H4: TOTAL
B5: INCOME
B6: Product sales | C6: =SUMIFS(Transactions!$F$4:$F$1003,Transactions!$B$4:$B$1003,Setup!$B$6,Transactions!$D$4:$D$1003,"Product sales",Transactions!$C$4:$C$1003,"Income") | D6: =SUMIFS(Transactions!$F$4:$F$1003,Transactions!$B$4:$B$1003,Setup!$B$7,Transactions!$D$4:$D$1003,"Product sales",Transactions!$C$4:$C$1003,"Income") | E6: =SUMIFS(Transactions!$F$4:$F$1003,Transactions!$B$4:$B$1003,Setup!$B$8,Transactions!$D$4:$D$1003,"Product sales",Transactions!$C$4:$C$1003,"Income") | F6: =SUMIFS(Transactions!$F$4:$F$1003,Transactions!$B$4:$B$1003,Setup!$B$9,Transactions!$D$4:$D$1003,"Product sales",Transactions!$C$4:$C$1003,"Income") | G6: =SUMIFS(Transactions!$F$4:$F$1003,Transactions!$B$4:$B$1003,Setup!$B$10,Transactions!$D$4:$D$1003,"Product sales",Transactions!$C$4:$C$1003,"Income") | H6: =SUM(C6:G6)
B7: Shipping income collected | C7: =SUMIFS(Transactions!$F$4:$F$1003,Transactions!$B$4:$B$1003,Setup!$B$6,Transactions!$D$4:$D$1003,"Shipping income collected",Transactions!$C$4:$C$1003,"Income") | D7: =SUMIFS(Transactions!$F$4:$F$1003,Transactions!$B$4:$B$1003,Setup!$B$7,Transactions!$D$4:$D$1003,"Shipping income collected",Transactions!$C$4:$C$1003,"Income") | E7: =SUMIFS(Transactions!$F$4:$F$1003,Transactions!$B$4:$B$1003,Setup!$B$8,Transactions!$D$4:$D$1003,"Shipping income collected",Transactions!$C$4:$C$1003,"Income") | F7: =SUMIFS(Transactions!$F$4:$F$1003,Transactions!$B$4:$B$1003,Setup!$B$9,Transactions!$D$4:$D$1003,"Shipping income collected",Transactions!$C$4:$C$1003,"Income") | G7: =SUMIFS(Transactions!$F$4:$F$1003,Transactions!$B$4:$B$1003,Setup!$B$10,Transactions!$D$4:$D$1003,"Shipping income collected",Transactions!$C$4:$C$1003,"Income") | H7: =SUM(C7:G7)
B8: Other income | C8: =SUMIFS(Transactions!$F$4:$F$1003,Transactions!$B$4:$B$1003,Setup!$B$6,Transactions!$D$4:$D$1003,"Other income",Transactions!$C$4:$C$1003,"Income") | D8: =SUMIFS(Transactions!$F$4:$F$1003,Transactions!$B$4:$B$1003,Setup!$B$7,Transactions!$D$4:$D$1003,"Other income",Transactions!$C$4:$C$1003,"Income") | E8: =SUMIFS(Transactions!$F$4:$F$1003,Transactions!$B$4:$B$1003,Setup!$B$8,Transactions!$D$4:$D$1003,"Other income",Transactions!$C$4:$C$1003,"Income") | F8: =SUMIFS(Transactions!$F$4:$F$1003,Transactions!$B$4:$B$1003,Setup!$B$9,Transactions!$D$4:$D$1003,"Other income",Transactions!$C$4:$C$1003,"Income") | G8: =SUMIFS(Transactions!$F$4:$F$1003,Transactions!$B$4:$B$1003,Setup!$B$10,Transactions!$D$4:$D$1003,"Other income",Transactions!$C$4:$C$1003,"Income") | H8: =SUM(C8:G8)
B9: Total income (Line 1) | C9: =SUM(C6:C8) | D9: =SUM(D6:D8) | E9: =SUM(E6:E8) | F9: =SUM(F6:F8) | G9: =SUM(G6:G8) | H9: =SUM(H6:H8)
B11: EXPENSES
B12: 8 Advertising | C12: =SUMIFS(Transactions!$F$4:$F$1003,Transactions!$B$4:$B$1003,Setup!$B$6,Transactions!$D$4:$D$1003,"Advertising & promotion",Transactions!$C$4:$C$1003,"Expense") | D12: =SUMIFS(Transactions!$F$4:$F$1003,Transactions!$B$4:$B$1003,Setup!$B$7,Transactions!$D$4:$D$1003,"Advertising & promotion",Transactions!$C$4:$C$1003,"Expense") | E12: =SUMIFS(Transactions!$F$4:$F$1003,Transactions!$B$4:$B$1003,Setup!$B$8,Transactions!$D$4:$D$1003,"Advertising & promotion",Transactions!$C$4:$C$1003,"Expense") | F12: =SUMIFS(Transactions!$F$4:$F$1003,Transactions!$B$4:$B$1003,Setup!$B$9,Transactions!$D$4:$D$1003,"Advertising & promotion",Transactions!$C$4:$C$1003,"Expense") | G12: =SUMIFS(Transactions!$F$4:$F$1003,Transactions!$B$4:$B$1003,Setup!$B$10,Transactions!$D$4:$D$1003,"Advertising & promotion",Transactions!$C$4:$C$1003,"Expense") | H12: =SUM(C12:G12)
B13: 9 Car & truck | C13: =SUMIFS(Transactions!$F$4:$F$1003,Transactions!$B$4:$B$1003,Setup!$B$6,Transactions!$D$4:$D$1003,"Car & truck",Transactions!$C$4:$C$1003,"Expense") | D13: =SUMIFS(Transactions!$F$4:$F$1003,Transactions!$B$4:$B$1003,Setup!$B$7,Transactions!$D$4:$D$1003,"Car & truck",Transactions!$C$4:$C$1003,"Expense") | E13: =SUMIFS(Transactions!$F$4:$F$1003,Transactions!$B$4:$B$1003,Setup!$B$8,Transactions!$D$4:$D$1003,"Car & truck",Transactions!$C$4:$C$1003,"Expense") | F13: =SUMIFS(Transactions!$F$4:$F$1003,Transactions!$B$4:$B$1003,Setup!$B$9,Transactions!$D$4:$D$1003,"Car & truck",Transactions!$C$4:$C$1003,"Expense") | G13: =SUMIFS(Transactions!$F$4:$F$1003,Transactions!$B$4:$B$1003,Setup!$B$10,Transactions!$D$4:$D$1003,"Car & truck",Transactions!$C$4:$C$1003,"Expense") | H13: =SUM(C13:G13)
B14: 10 Commissions & fees | C14: =SUMIFS(Transactions!$F$4:$F$1003,Transactions!$B$4:$B$1003,Setup!$B$6,Transactions!$D$4:$D$1003,"Commissions & marketplace fees",Transactions!$C$4:$C$1003,"Expense") | D14: =SUMIFS(Transactions!$F$4:$F$1003,Transactions!$B$4:$B$1003,Setup!$B$7,Transactions!$D$4:$D$1003,"Commissions & marketplace fees",Transactions!$C$4:$C$1003,"Expense") | E14: =SUMIFS(Transactions!$F$4:$F$1003,Transactions!$B$4:$B$1003,Setup!$B$8,Transactions!$D$4:$D$1003,"Commissions & marketplace fees",Transactions!$C$4:$C$1003,"Expense") | F14: =SUMIFS(Transactions!$F$4:$F$1003,Transactions!$B$4:$B$1003,Setup!$B$9,Transactions!$D$4:$D$1003,"Commissions & marketplace fees",Transactions!$C$4:$C$1003,"Expense") | G14: =SUMIFS(Transactions!$F$4:$F$1003,Transactions!$B$4:$B$1003,Setup!$B$10,Transactions!$D$4:$D$1003,"Commissions & marketplace fees",Transactions!$C$4:$C$1003,"Expense") | H14: =SUM(C14:G14)
B15: 11 Contract labor | C15: =SUMIFS(Transactions!$F$4:$F$1003,Transactions!$B$4:$B$1003,Setup!$B$6,Transactions!$D$4:$D$1003,"Contract labor",Transactions!$C$4:$C$1003,"Expense") | D15: =SUMIFS(Transactions!$F$4:$F$1003,Transactions!$B$4:$B$1003,Setup!$B$7,Transactions!$D$4:$D$1003,"Contract labor",Transactions!$C$4:$C$1003,"Expense") | E15: =SUMIFS(Transactions!$F$4:$F$1003,Transactions!$B$4:$B$1003,Setup!$B$8,Transactions!$D$4:$D$1003,"Contract labor",Transactions!$C$4:$C$1003,"Expense") | F15: =SUMIFS(Transactions!$F$4:$F$1003,Transactions!$B$4:$B$1003,Setup!$B$9,Transactions!$D$4:$D$1003,"Contract labor",Transactions!$C$4:$C$1003,"Expense") | G15: =SUMIFS(Transactions!$F$4:$F$1003,Transactions!$B$4:$B$1003,Setup!$B$10,Transactions!$D$4:$D$1003,"Contract labor",Transactions!$C$4:$C$1003,"Expense") | H15: =SUM(C15:G15)
B16: 4 Cost of goods sold | C16: =SUMIFS(Transactions!$F$4:$F$1003,Transactions!$B$4:$B$1003,Setup!$B$6,Transactions!$D$4:$D$1003,"Cost of goods sold (materials)",Transactions!$C$4:$C$1003,"Expense") | D16: =SUMIFS(Transactions!$F$4:$F$1003,Transactions!$B$4:$B$1003,Setup!$B$7,Transactions!$D$4:$D$1003,"Cost of goods sold (materials)",Transactions!$C$4:$C$1003,"Expense") | E16: =SUMIFS(Transactions!$F$4:$F$1003,Transactions!$B$4:$B$1003,Setup!$B$8,Transactions!$D$4:$D$1003,"Cost of goods sold (materials)",Transactions!$C$4:$C$1003,"Expense") | F16: =SUMIFS(Transactions!$F$4:$F$1003,Transactions!$B$4:$B$1003,Setup!$B$9,Transactions!$D$4:$D$1003,"Cost of goods sold (materials)",Transactions!$C$4:$C$1003,"Expense") | G16: =SUMIFS(Transactions!$F$4:$F$1003,Transactions!$B$4:$B$1003,Setup!$B$10,Transactions!$D$4:$D$1003,"Cost of goods sold (materials)",Transactions!$C$4:$C$1003,"Expense") | H16: =SUM(C16:G16)
B17: 15 Insurance | C17: =SUMIFS(Transactions!$F$4:$F$1003,Transactions!$B$4:$B$1003,Setup!$B$6,Transactions!$D$4:$D$1003,"Insurance (business)",Transactions!$C$4:$C$1003,"Expense") | D17: =SUMIFS(Transactions!$F$4:$F$1003,Transactions!$B$4:$B$1003,Setup!$B$7,Transactions!$D$4:$D$1003,"Insurance (business)",Transactions!$C$4:$C$1003,"Expense") | E17: =SUMIFS(Transactions!$F$4:$F$1003,Transactions!$B$4:$B$1003,Setup!$B$8,Transactions!$D$4:$D$1003,"Insurance (business)",Transactions!$C$4:$C$1003,"Expense") | F17: =SUMIFS(Transactions!$F$4:$F$1003,Transactions!$B$4:$B$1003,Setup!$B$9,Transactions!$D$4:$D$1003,"Insurance (business)",Transactions!$C$4:$C$1003,"Expense") | G17: =SUMIFS(Transactions!$F$4:$F$1003,Transactions!$B$4:$B$1003,Setup!$B$10,Transactions!$D$4:$D$1003,"Insurance (business)",Transactions!$C$4:$C$1003,"Expense") | H17: =SUM(C17:G17)
B18: 17 Legal & professional | C18: =SUMIFS(Transactions!$F$4:$F$1003,Transactions!$B$4:$B$1003,Setup!$B$6,Transactions!$D$4:$D$1003,"Legal & professional",Transactions!$C$4:$C$1003,"Expense") | D18: =SUMIFS(Transactions!$F$4:$F$1003,Transactions!$B$4:$B$1003,Setup!$B$7,Transactions!$D$4:$D$1003,"Legal & professional",Transactions!$C$4:$C$1003,"Expense") | E18: =SUMIFS(Transactions!$F$4:$F$1003,Transactions!$B$4:$B$1003,Setup!$B$8,Transactions!$D$4:$D$1003,"Legal & professional",Transactions!$C$4:$C$1003,"Expense") | F18: =SUMIFS(Transactions!$F$4:$F$1003,Transactions!$B$4:$B$1003,Setup!$B$9,Transactions!$D$4:$D$1003,"Legal & professional",Transactions!$C$4:$C$1003,"Expense") | G18: =SUMIFS(Transactions!$F$4:$F$1003,Transactions!$B$4:$B$1003,Setup!$B$10,Transactions!$D$4:$D$1003,"Legal & professional",Transactions!$C$4:$C$1003,"Expense") | H18: =SUM(C18:G18)
B19: 18 Office expense | C19: =SUMIFS(Transactions!$F$4:$F$1003,Transactions!$B$4:$B$1003,Setup!$B$6,Transactions!$D$4:$D$1003,"Office expense",Transactions!$C$4:$C$1003,"Expense") | D19: =SUMIFS(Transactions!$F$4:$F$1003,Transactions!$B$4:$B$1003,Setup!$B$7,Transactions!$D$4:$D$1003,"Office expense",Transactions!$C$4:$C$1003,"Expense") | E19: =SUMIFS(Transactions!$F$4:$F$1003,Transactions!$B$4:$B$1003,Setup!$B$8,Transactions!$D$4:$D$1003,"Office expense",Transactions!$C$4:$C$1003,"Expense") | F19: =SUMIFS(Transactions!$F$4:$F$1003,Transactions!$B$4:$B$1003,Setup!$B$9,Transactions!$D$4:$D$1003,"Office expense",Transactions!$C$4:$C$1003,"Expense") | G19: =SUMIFS(Transactions!$F$4:$F$1003,Transactions!$B$4:$B$1003,Setup!$B$10,Transactions!$D$4:$D$1003,"Office expense",Transactions!$C$4:$C$1003,"Expense") | H19: =SUM(C19:G19)
B20: 20 Rent or lease | C20: =SUMIFS(Transactions!$F$4:$F$1003,Transactions!$B$4:$B$1003,Setup!$B$6,Transactions!$D$4:$D$1003,"Rent or lease",Transactions!$C$4:$C$1003,"Expense") | D20: =SUMIFS(Transactions!$F$4:$F$1003,Transactions!$B$4:$B$1003,Setup!$B$7,Transactions!$D$4:$D$1003,"Rent or lease",Transactions!$C$4:$C$1003,"Expense") | E20: =SUMIFS(Transactions!$F$4:$F$1003,Transactions!$B$4:$B$1003,Setup!$B$8,Transactions!$D$4:$D$1003,"Rent or lease",Transactions!$C$4:$C$1003,"Expense") | F20: =SUMIFS(Transactions!$F$4:$F$1003,Transactions!$B$4:$B$1003,Setup!$B$9,Transactions!$D$4:$D$1003,"Rent or lease",Transactions!$C$4:$C$1003,"Expense") | G20: =SUMIFS(Transactions!$F$4:$F$1003,Transactions!$B$4:$B$1003,Setup!$B$10,Transactions!$D$4:$D$1003,"Rent or lease",Transactions!$C$4:$C$1003,"Expense") | H20: =SUM(C20:G20)
B21: 21 Repairs & maintenance | C21: =SUMIFS(Transactions!$F$4:$F$1003,Transactions!$B$4:$B$1003,Setup!$B$6,Transactions!$D$4:$D$1003,"Repairs & maintenance",Transactions!$C$4:$C$1003,"Expense") | D21: =SUMIFS(Transactions!$F$4:$F$1003,Transactions!$B$4:$B$1003,Setup!$B$7,Transactions!$D$4:$D$1003,"Repairs & maintenance",Transactions!$C$4:$C$1003,"Expense") | E21: =SUMIFS(Transactions!$F$4:$F$1003,Transactions!$B$4:$B$1003,Setup!$B$8,Transactions!$D$4:$D$1003,"Repairs & maintenance",Transactions!$C$4:$C$1003,"Expense") | F21: =SUMIFS(Transactions!$F$4:$F$1003,Transactions!$B$4:$B$1003,Setup!$B$9,Transactions!$D$4:$D$1003,"Repairs & maintenance",Transactions!$C$4:$C$1003,"Expense") | G21: =SUMIFS(Transactions!$F$4:$F$1003,Transactions!$B$4:$B$1003,Setup!$B$10,Transactions!$D$4:$D$1003,"Repairs & maintenance",Transactions!$C$4:$C$1003,"Expense") | H21: =SUM(C21:G21)
B22: 27 Other (shipping) | C22: =SUMIFS(Transactions!$F$4:$F$1003,Transactions!$B$4:$B$1003,Setup!$B$6,Transactions!$D$4:$D$1003,"Shipping & postage",Transactions!$C$4:$C$1003,"Expense") | D22: =SUMIFS(Transactions!$F$4:$F$1003,Transactions!$B$4:$B$1003,Setup!$B$7,Transactions!$D$4:$D$1003,"Shipping & postage",Transactions!$C$4:$C$1003,"Expense") | E22: =SUMIFS(Transactions!$F$4:$F$1003,Transactions!$B$4:$B$1003,Setup!$B$8,Transactions!$D$4:$D$1003,"Shipping & postage",Transactions!$C$4:$C$1003,"Expense") | F22: =SUMIFS(Transactions!$F$4:$F$1003,Transactions!$B$4:$B$1003,Setup!$B$9,Transactions!$D$4:$D$1003,"Shipping & postage",Transactions!$C$4:$C$1003,"Expense") | G22: =SUMIFS(Transactions!$F$4:$F$1003,Transactions!$B$4:$B$1003,Setup!$B$10,Transactions!$D$4:$D$1003,"Shipping & postage",Transactions!$C$4:$C$1003,"Expense") | H22: =SUM(C22:G22)
B23: 27 Other (software) | C23: =SUMIFS(Transactions!$F$4:$F$1003,Transactions!$B$4:$B$1003,Setup!$B$6,Transactions!$D$4:$D$1003,"Software & subscriptions",Transactions!$C$4:$C$1003,"Expense") | D23: =SUMIFS(Transactions!$F$4:$F$1003,Transactions!$B$4:$B$1003,Setup!$B$7,Transactions!$D$4:$D$1003,"Software & subscriptions",Transactions!$C$4:$C$1003,"Expense") | E23: =SUMIFS(Transactions!$F$4:$F$1003,Transactions!$B$4:$B$1003,Setup!$B$8,Transactions!$D$4:$D$1003,"Software & subscriptions",Transactions!$C$4:$C$1003,"Expense") | F23: =SUMIFS(Transactions!$F$4:$F$1003,Transactions!$B$4:$B$1003,Setup!$B$9,Transactions!$D$4:$D$1003,"Software & subscriptions",Transactions!$C$4:$C$1003,"Expense") | G23: =SUMIFS(Transactions!$F$4:$F$1003,Transactions!$B$4:$B$1003,Setup!$B$10,Transactions!$D$4:$D$1003,"Software & subscriptions",Transactions!$C$4:$C$1003,"Expense") | H23: =SUM(C23:G23)
B24: 22 Supplies | C24: =SUMIFS(Transactions!$F$4:$F$1003,Transactions!$B$4:$B$1003,Setup!$B$6,Transactions!$D$4:$D$1003,"Supplies & packaging",Transactions!$C$4:$C$1003,"Expense") | D24: =SUMIFS(Transactions!$F$4:$F$1003,Transactions!$B$4:$B$1003,Setup!$B$7,Transactions!$D$4:$D$1003,"Supplies & packaging",Transactions!$C$4:$C$1003,"Expense") | E24: =SUMIFS(Transactions!$F$4:$F$1003,Transactions!$B$4:$B$1003,Setup!$B$8,Transactions!$D$4:$D$1003,"Supplies & packaging",Transactions!$C$4:$C$1003,"Expense") | F24: =SUMIFS(Transactions!$F$4:$F$1003,Transactions!$B$4:$B$1003,Setup!$B$9,Transactions!$D$4:$D$1003,"Supplies & packaging",Transactions!$C$4:$C$1003,"Expense") | G24: =SUMIFS(Transactions!$F$4:$F$1003,Transactions!$B$4:$B$1003,Setup!$B$10,Transactions!$D$4:$D$1003,"Supplies & packaging",Transactions!$C$4:$C$1003,"Expense") | H24: =SUM(C24:G24)
B25: 23 Taxes & licenses | C25: =SUMIFS(Transactions!$F$4:$F$1003,Transactions!$B$4:$B$1003,Setup!$B$6,Transactions!$D$4:$D$1003,"Taxes & licenses",Transactions!$C$4:$C$1003,"Expense") | D25: =SUMIFS(Transactions!$F$4:$F$1003,Transactions!$B$4:$B$1003,Setup!$B$7,Transactions!$D$4:$D$1003,"Taxes & licenses",Transactions!$C$4:$C$1003,"Expense") | E25: =SUMIFS(Transactions!$F$4:$F$1003,Transactions!$B$4:$B$1003,Setup!$B$8,Transactions!$D$4:$D$1003,"Taxes & licenses",Transactions!$C$4:$C$1003,"Expense") | F25: =SUMIFS(Transactions!$F$4:$F$1003,Transactions!$B$4:$B$1003,Setup!$B$9,Transactions!$D$4:$D$1003,"Taxes & licenses",Transactions!$C$4:$C$1003,"Expense") | G25: =SUMIFS(Transactions!$F$4:$F$1003,Transactions!$B$4:$B$1003,Setup!$B$10,Transactions!$D$4:$D$1003,"Taxes & licenses",Transactions!$C$4:$C$1003,"Expense") | H25: =SUM(C25:G25)
B26: 24 Travel & meals | C26: =SUMIFS(Transactions!$F$4:$F$1003,Transactions!$B$4:$B$1003,Setup!$B$6,Transactions!$D$4:$D$1003,"Travel & meals",Transactions!$C$4:$C$1003,"Expense") | D26: =SUMIFS(Transactions!$F$4:$F$1003,Transactions!$B$4:$B$1003,Setup!$B$7,Transactions!$D$4:$D$1003,"Travel & meals",Transactions!$C$4:$C$1003,"Expense") | E26: =SUMIFS(Transactions!$F$4:$F$1003,Transactions!$B$4:$B$1003,Setup!$B$8,Transactions!$D$4:$D$1003,"Travel & meals",Transactions!$C$4:$C$1003,"Expense") | F26: =SUMIFS(Transactions!$F$4:$F$1003,Transactions!$B$4:$B$1003,Setup!$B$9,Transactions!$D$4:$D$1003,"Travel & meals",Transactions!$C$4:$C$1003,"Expense") | G26: =SUMIFS(Transactions!$F$4:$F$1003,Transactions!$B$4:$B$1003,Setup!$B$10,Transactions!$D$4:$D$1003,"Travel & meals",Transactions!$C$4:$C$1003,"Expense") | H26: =SUM(C26:G26)
B27: 25 Utilities | C27: =SUMIFS(Transactions!$F$4:$F$1003,Transactions!$B$4:$B$1003,Setup!$B$6,Transactions!$D$4:$D$1003,"Utilities (phone/internet)",Transactions!$C$4:$C$1003,"Expense") | D27: =SUMIFS(Transactions!$F$4:$F$1003,Transactions!$B$4:$B$1003,Setup!$B$7,Transactions!$D$4:$D$1003,"Utilities (phone/internet)",Transactions!$C$4:$C$1003,"Expense") | E27: =SUMIFS(Transactions!$F$4:$F$1003,Transactions!$B$4:$B$1003,Setup!$B$8,Transactions!$D$4:$D$1003,"Utilities (phone/internet)",Transactions!$C$4:$C$1003,"Expense") | F27: =SUMIFS(Transactions!$F$4:$F$1003,Transactions!$B$4:$B$1003,Setup!$B$9,Transactions!$D$4:$D$1003,"Utilities (phone/internet)",Transactions!$C$4:$C$1003,"Expense") | G27: =SUMIFS(Transactions!$F$4:$F$1003,Transactions!$B$4:$B$1003,Setup!$B$10,Transactions!$D$4:$D$1003,"Utilities (phone/internet)",Transactions!$C$4:$C$1003,"Expense") | H27: =SUM(C27:G27)
B28: Total expenses (incl. COGS) | C28: =SUM(C12:C27) | D28: =SUM(D12:D27) | E28: =SUM(E12:E27) | F28: =SUM(F12:F27) | G28: =SUM(G12:G27) | H28: =SUM(H12:H27)
B29: NET PROFIT / (LOSS) | C29: =C9-C28 | D29: =D9-D28 | E29: =E9-E28 | F29: =F9-F28 | G29: =G9-G28 | H29: =H9-H28

Sheet Dashboard
B2: Dashboard — live overview
B4: Total income | C4: Total expenses | E4: Net profit / (loss)
B5: =SUMIFS(Transactions!$F$4:$F$1003,Transactions!$C$4:$C$1003,"Income") | C5: =SUMIFS(Transactions!$F$4:$F$1003,Transactions!$C$4:$C$1003,"Expense") | E5: =(SUMIFS(Transactions!$F$4:$F$1003,Transactions!$C$4:$C$1003,"Income"))-(SUMIFS(Transactions!$F$4:$F$1003,Transactions!$C$4:$C$1003,"Expense"))
B8: By shop | F8: By month (2026)
B9: Shop | C9: Income | D9: Expenses | E9: Net | F9: Month | G9: Income | H9: Expenses
B10: =Setup!$B$6 | C10: =SUMIFS(Transactions!$F$4:$F$1003,Transactions!$B$4:$B$1003,Setup!$B$6,Transactions!$C$4:$C$1003,"Income") | D10: =SUMIFS(Transactions!$F$4:$F$1003,Transactions!$B$4:$B$1003,Setup!$B$6,Transactions!$C$4:$C$1003,"Expense") | E10: =C10-D10 | F10: 2026-01 | G10: =SUMIFS(Transactions!$F$4:$F$1003,Transactions!$H$4:$H$1003,"2026-01",Transactions!$C$4:$C$1003,"Income") | H10: =SUMIFS(Transactions!$F$4:$F$1003,Transactions!$H$4:$H$1003,"2026-01",Transactions!$C$4:$C$1003,"Expense")
B11: =Setup!$B$7 | C11: =SUMIFS(Transactions!$F$4:$F$1003,Transactions!$B$4:$B$1003,Setup!$B$7,Transactions!$C$4:$C$1003,"Income") | D11: =SUMIFS(Transactions!$F$4:$F$1003,Transactions!$B$4:$B$1003,Setup!$B$7,Transactions!$C$4:$C$1003,"Expense") | E11: =C11-D11 | F11: 2026-02 | G11: =SUMIFS(Transactions!$F$4:$F$1003,Transactions!$H$4:$H$1003,"2026-02",Transactions!$C$4:$C$1003,"Income") | H11: =SUMIFS(Transactions!$F$4:$F$1003,Transactions!$H$4:$H$1003,"2026-02",Transactions!$C$4:$C$1003,"Expense")
B12: =Setup!$B$8 | C12: =SUMIFS(Transactions!$F$4:$F$1003,Transactions!$B$4:$B$1003,Setup!$B$8,Transactions!$C$4:$C$1003,"Income") | D12: =SUMIFS(Transactions!$F$4:$F$1003,Transactions!$B$4:$B$1003,Setup!$B$8,Transactions!$C$4:$C$1003,"Expense") | E12: =C12-D12 | F12: 2026-03 | G12: =SUMIFS(Transactions!$F$4:$F$1003,Transactions!$H$4:$H$1003,"2026-03",Transactions!$C$4:$C$1003,"Income") | H12: =SUMIFS(Transactions!$F$4:$F$1003,Transactions!$H$4:$H$1003,"2026-03",Transactions!$C$4:$C$1003,"Expense")
B13: =Setup!$B$9 | C13: =SUMIFS(Transactions!$F$4:$F$1003,Transactions!$B$4:$B$1003,Setup!$B$9,Transactions!$C$4:$C$1003,"Income") | D13: =SUMIFS(Transactions!$F$4:$F$1003,Transactions!$B$4:$B$1003,Setup!$B$9,Transactions!$C$4:$C$1003,"Expense") | E13: =C13-D13 | F13: 2026-04 | G13: =SUMIFS(Transactions!$F$4:$F$1003,Transactions!$H$4:$H$1003,"2026-04",Transactions!$C$4:$C$1003,"Income") | H13: =SUMIFS(Transactions!$F$4:$F$1003,Transactions!$H$4:$H$1003,"2026-04",Transactions!$C$4:$C$1003,"Expense")
B14: =Setup!$B$10 | C14: =SUMIFS(Transactions!$F$4:$F$1003,Transactions!$B$4:$B$1003,Setup!$B$10,Transactions!$C$4:$C$1003,"Income") | D14: =SUMIFS(Transactions!$F$4:$F$1003,Transactions!$B$4:$B$1003,Setup!$B$10,Transactions!$C$4:$C$1003,"Expense") | E14: =C14-D14 | F14: 2026-05 | G14: =SUMIFS(Transactions!$F$4:$F$1003,Transactions!$H$4:$H$1003,"2026-05",Transactions!$C$4:$C$1003,"Income") | H14: =SUMIFS(Transactions!$F$4:$F$1003,Transactions!$H$4:$H$1003,"2026-05",Transactions!$C$4:$C$1003,"Expense")
B15: All shops | C15: =SUM(C10:C14) | D15: =SUM(D10:D14) | E15: =SUM(E10:E14) | F15: 2026-06 | G15: =SUMIFS(Transactions!$F$4:$F$1003,Transactions!$H$4:$H$1003,"2026-06",Transactions!$C$4:$C$1003,"Income") | H15: =SUMIFS(Transactions!$F$4:$F$1003,Transactions!$H$4:$H$1003,"2026-06",Transactions!$C$4:$C$1003,"Expense")
F16: 2026-07 | G16: =SUMIFS(Transactions!$F$4:$F$1003,Transactions!$H$4:$H$1003,"2026-07",Transactions!$C$4:$C$1003,"Income") | H16: =SUMIFS(Transactions!$F$4:$F$1003,Transactions!$H$4:$H$1003,"2026-07",Transactions!$C$4:$C$1003,"Expense")
F17: 2026-08 | G17: =SUMIFS(Transactions!$F$4:$F$1003,Transactions!$H$4:$H$1003,"2026-08",Transactions!$C$4:$C$1003,"Income") | H17: =SUMIFS(Transactions!$F$4:$F$1003,Transactions!$H$4:$H$1003,"2026-08",Transactions!$C$4:$C$1003,"Expense")
F18: 2026-09 | G18: =SUMIFS(Transactions!$F$4:$F$1003,Transactions!$H$4:$H$1003,"2026-09",Transactions!$C$4:$C$1003,"Income") | H18: =SUMIFS(Transactions!$F$4:$F$1003,Transactions!$H$4:$H$1003,"2026-09",Transactions!$C$4:$C$1003,"Expense")
F19: 2026-10 | G19: =SUMIFS(Transactions!$F$4:$F$1003,Transactions!$H$4:$H$1003,"2026-10",Transactions!$C$4:$C$1003,"Income") | H19: =SUMIFS(Transactions!$F$4:$F$1003,Transactions!$H$4:$H$1003,"2026-10",Transactions!$C$4:$C$1003,"Expense")
F20: 2026-11 | G20: =SUMIFS(Transactions!$F$4:$F$1003,Transactions!$H$4:$H$1003,"2026-11",Transactions!$C$4:$C$1003,"Income") | H20: =SUMIFS(Transactions!$F$4:$F$1003,Transactions!$H$4:$H$1003,"2026-11",Transactions!$C$4:$C$1003,"Expense")
F21: 2026-12 | G21: =SUMIFS(Transactions!$F$4:$F$1003,Transactions!$H$4:$H$1003,"2026-12",Transactions!$C$4:$C$1003,"Income") | H21: =SUMIFS(Transactions!$F$4:$F$1003,Transactions!$H$4:$H$1003,"2026-12",Transactions!$C$4:$C$1003,"Expense")
